VoxCeleb/__init__.py
VoxCeleb/_version.py
VoxCeleb/data/verif_exhaustive.txt.gz
VoxCeleb/data/verif_hard.txt.gz
VoxCeleb/data/verif_original.txt.gz
VoxCeleb/data/verif_x.txt.gz
VoxCeleb/data/vox1_dev_duration.txt.gz
VoxCeleb/data/vox1_identities.txt.gz
VoxCeleb/data/vox1_tst_duration.txt.gz
VoxCeleb/data/vox1_xdev_duration.txt.gz
VoxCeleb/data/vox1_xtrn_duration.txt.gz
VoxCeleb/data/vox2_dev_duration.txt.gz
VoxCeleb/data/vox2_meta.csv.gz
VoxCeleb/data/vox2_tst_duration.txt.gz
VoxCeleb/data/voxceleb1.verification.dev.csv
pyannote.db.voxceleb-1.3.1.dist-info/LICENSE
pyannote.db.voxceleb-1.3.1.dist-info/METADATA
pyannote.db.voxceleb-1.3.1.dist-info/WHEEL
pyannote.db.voxceleb-1.3.1.dist-info/entry_points.txt
pyannote.db.voxceleb-1.3.1.dist-info/top_level.txt
pyannote.db.voxceleb-1.3.1.dist-info/RECORD
